hg_confman-2.1.0-py3.11-nspkg.pth
hgext3rd/confman/__init__.py
hgext3rd/confman/commands.py
hgext3rd/confman/configuration.py
hgext3rd/confman/forge.py
hgext3rd/confman/gr.py
hgext3rd/confman/hgcompat.py
hgext3rd/confman/managed.py
hgext3rd/confman/meta.py
hgext3rd/confman/opts.py
hgext3rd/confman/runner.py
hgext3rd/confman/utils.py
hg_confman-2.1.0.dist-info/COPYING
hg_confman-2.1.0.dist-info/METADATA
hg_confman-2.1.0.dist-info/WHEEL
hg_confman-2.1.0.dist-info/namespace_packages.txt
hg_confman-2.1.0.dist-info/top_level.txt
hg_confman-2.1.0.dist-info/RECORD
