Metadata-Version: 2.1
Name: hg-confman
Version: 2.1.0
Summary: Configuration management tool
Home-page: https://hg.sr.ht/~auc/confman
Author: Aurélien Campéas
Author-email: aurelien.campeas@pythonian.fr
License: GPLv2+
Keywords: hg mercurial
Classifier: Development Status :: 6 - Mature
Classifier: Intended Audience :: Developers
Classifier: License :: OSI Approved :: GNU General Public License v2 or later (GPLv2+)
Classifier: Operating System :: OS Independent
Classifier: Programming Language :: Python :: 3
Classifier: Topic :: Software Development :: Version Control
Classifier: Topic :: Software Development :: Version Control :: Mercurial
License-File: COPYING
